gradio_editor3d/__init__.py
gradio_editor3d/editor3d.py
gradio_editor3d/editor3d.pyi
gradio_editor3d/templates/component/index.js
gradio_editor3d/templates/component/style.css
gradio_editor3d/templates/example/index.js
gradio_editor3d/templates/example/style.css
gradio_editor3d-0.0.3.dist-info/METADATA
gradio_editor3d-0.0.3.dist-info/WHEEL
gradio_editor3d-0.0.3.dist-info/RECORD
